safir/asyncio/__init__.py
safir/asyncio/_multiqueue.py
safir/asyncio/_run.py
safir/asyncio/py.typed
safir/click/__init__.py
safir/click/_help.py
safir/click/py.typed
safir/database/__init__.py
safir/database/_alembic.py
safir/database/_connection.py
safir/database/_datetime.py
safir/database/_initialize.py
safir/database/_pagination.py
safir/database/_retry.py
safir/database/py.typed
safir/datetime/__init__.py
safir/datetime/_current.py
safir/datetime/_format.py
safir/datetime/_parse.py
safir/datetime/py.typed
safir/dependencies/__init__.py
safir/dependencies/arq.py
safir/dependencies/db_session.py
safir/dependencies/gafaelfawr.py
safir/dependencies/http_client.py
safir/dependencies/logger.py
safir/dependencies/metrics.py
safir/dependencies/py.typed
safir/fastapi/__init__.py
safir/fastapi/_errors.py
safir/fastapi/py.typed
safir/gcs/__init__.py
safir/gcs/_signing.py
safir/gcs/py.typed
safir/github/__init__.py
safir/github/_client.py
safir/github/models.py
safir/github/py.typed
safir/github/webhooks.py
safir/kafka/__init__.py
safir/kafka/_exceptions.py
safir/kafka/_kafka_config.py
safir/kafka/_manager.py
safir/kafka/_schema_registry_config.py
safir/kafka/py.typed
safir/kubernetes/__init__.py
safir/kubernetes/_init.py
safir/kubernetes/py.typed
safir/metadata/__init__.py
safir/metadata/_models.py
safir/metadata/_retrieve.py
safir/metadata/py.typed
safir/metrics/__init__.py
safir/metrics/_config.py
safir/metrics/_constants.py
safir/metrics/_event_manager.py
safir/metrics/_exceptions.py
safir/metrics/_models.py
safir/metrics/_testing.py
safir/metrics/arq.py
safir/metrics/py.typed
safir/middleware/__init__.py
safir/middleware/ivoa.py
safir/middleware/py.typed
safir/middleware/x_forwarded.py
safir/models/__init__.py
safir/models/_errors.py
safir/models/py.typed
safir/pydantic/__init__.py
safir/pydantic/_camel.py
safir/pydantic/_types.py
safir/pydantic/_validators.py
safir/pydantic/py.typed
safir/redis/__init__.py
safir/redis/_storage.py
safir/redis/py.typed
safir-14.2.0.dist-info/licenses/LICENSE
safir-14.2.0.dist-info/METADATA
safir-14.2.0.dist-info/WHEEL
safir-14.2.0.dist-info/top_level.txt
safir-14.2.0.dist-info/RECORD
